{
  "version": 1,
  "views": [
    {
      "id": "73b6524f-33c5-4e3e-bf42-c995d88fb33f",
      "title": null,
      "createdAt": 1782284534470,
      "updatedAt": 1782307349837,
      "sessionId": null,
      "source": "user",
      "diagramType": "flowchart",
      "canvas": {
        "diagramType": "flowchart",
        "nodes": [
          {
            "id": "subgraph_1782306896445",
            "type": "subgraph",
            "position": {
              "x": 15,
              "y": 20
            },
            "data": {
              "label": "新子图",
              "shape": "rect",
              "isSubgraph": true,
              "subgraphNodes": [
                "node_1782306894700_0"
              ],
              "_sourceLine": 3
            },
            "width": 200,
            "height": 196,
            "measured": {
              "width": 200,
              "height": 196
            }
          },
          {
            "id": "node_1782306894700_0",
            "type": "default",
            "position": {
              "x": 45,
              "y": 88
            },
            "data": {
              "label": "新节点",
              "shape": "rect",
              "_sourceLine": 4
            },
            "parentId": "subgraph_1782306896445",
            "width": 108,
            "height": 48,
            "measured": {
              "width": 108,
              "height": 48
            },
            "selected": false
          }
        ],
        "edges": [],
        "direction": "TD"
      },
      "consumed": {
        "consumed": false,
        "lastConsumedAt": null,
        "canvasSource": "user"
      },
      "viewport": {
        "x": 167.5,
        "y": 356,
        "zoom": 2
      }
    }
  ],
  "activeViewId": "73b6524f-33c5-4e3e-bf42-c995d88fb33f"
}